[{"symbol":"NQ","timeframe":"1M","time":928188000,"open":2293.5,"high":2348.5,"low":2268.5,"close":2325.5,"Volume":2456,"Volume MA":"NaN"},{"symbol":"NQ","timeframe":"1M","time":930780000,"open":2326,"high":2489,"low":2265.5,"close":2294,"Volume":57920,"Volume MA":"NaN"},{"symbol":"NQ","timeframe":"1M","time":933544800,"open":2266.5,"high":2477.5,"low":2132,"close":2395.5,"Volume":83324,"Volume MA":"NaN"},{"symbol":"NQ","timeframe":"1M","time":936136800,"open":2395,"high":2588,"low":2362,"close":2439.5,"Volume":89004,"Volume MA":"NaN"},{"symbol":"NQ","timeframe":"1M","time":938728800,"open":2436.5,"high":2672,"low":2318.5,"close":2655.5,"Volume":104355,"Volume MA":"NaN"},{"symbol":"NQ","timeframe":"1M","time":941410800,"open":2650,"high":3165,"low":2626.5,"close":2972,"Volume":120691,"Volume MA":"NaN"},{"symbol":"NQ","timeframe":"1M","time":944002800,"open":2971,"high":3804.5,"low":2961.5,"close":3754,"Volume":181857,"Volume MA":"NaN"},{"symbol":"NQ","timeframe":"1M","time":946854000,"open":3750,"high":3938,"low":3257,"close":3612.5,"Volume":301193,"Volume MA":"NaN"},{"symbol":"NQ","timeframe":"1M","time":949359600,"open":3606.5,"high":4316,"low":3564,"close":4301,"Volume":386267,"Volume MA":"NaN"},{"symbol":"NQ","timeframe":"1M","time":951865200,"open":4298,"high":4884,"low":4108,"close":4457.5,"Volume":572577,"Volume MA":"NaN"},{"symbol":"NQ","timeframe":"1M","time":954712800,"open":4417,"high":4417,"low":3148,"close":3810,"Volume":599269,"Volume MA":"NaN"},{"symbol":"NQ","timeframe":"1M","time":957132000,"open":3807.5,"high":3910,"low":2902.5,"close":3325,"Volume":744705,"Volume MA":"NaN"},{"symbol":"NQ","timeframe":"1M","time":959810400,"open":3324,"high":4057.5,"low":3324,"close":3817,"Volume":730109,"Volume MA":"NaN"},{"symbol":"NQ","timeframe":"1M","time":962575200,"open":3801.5,"high":4134.5,"low":3464.5,"close":3617,"Volume":755886,"Volume MA":"NaN"},{"symbol":"NQ","timeframe":"1M","time":965080800,"open":3616,"high":4095,"low":3370,"close":4094,"Volume":883112,"Volume MA":"NaN"},{"symbol":"NQ","timeframe":"1M","time":967759200,"open":4089.5,"high":4186,"low":3580.5,"close":3621,"Volume":1162841,"Volume MA":"NaN"},{"symbol":"NQ","timeframe":"1M","time":970437600,"open":3621,"high":3668,"low":2978.5,"close":3298,"Volume":1588826,"Volume MA":"NaN"},{"symbol":"NQ","timeframe":"1M","time":973033200,"open":3299.5,"high":3400,"low":2435,"close":2530,"Volume":1518227,"Volume MA":"NaN"},{"symbol":"NQ","timeframe":"1M","time":975625200,"open":2530.5,"high":3048,"low":2211,"close":2374.5,"Volume":1437234,"Volume MA":"NaN"},{"symbol":"NQ","timeframe":"1M","time":978303600,"open":2375,"high":2797,"low":2130.5,"close":2611,"Volume":1879203,"Volume MA":659952.8},{"symbol":"NQ","timeframe":"1M","time":980982000,"open":2608.5,"high":2647.5,"low":1881,"close":1913,"Volume":1941199,"Volume MA":756889.95},{"symbol":"NQ","timeframe":"1M","time":983401200,"open":1905.5,"high":2036.5,"low":1544.5,"close":1588,"Volume":2500483,"Volume MA":879018.1},{"symbol":"NQ","timeframe":"1M","time":986162400,"open":1601,"high":1997,"low":1361,"close":1866.5,"Volume":2923006,"Volume MA":1021002.2},{"symbol":"NQ","timeframe":"1M","time":988668000,"open":1862,"high":2080.5,"low":1764,"close":1798.5,"Volume":2795588,"Volume MA":1156331.4},{"symbol":"NQ","timeframe":"1M","time":991346400,"open":1799,"high":2022.5,"low":1660,"close":1855,"Volume":2821677,"Volume MA":1292197.5},{"symbol":"NQ","timeframe":"1M","time":994024800,"open":1848,"high":1882,"low":1588.5,"close":1693,"Volume":2475685,"Volume MA":1409947.2},{"symbol":"NQ","timeframe":"1M","time":996616800,"open":1691,"high":1779.5,"low":1437,"close":1472.5,"Volume":2567569,"Volume MA":1529232.8},{"symbol":"NQ","timeframe":"1M","time":999468000,"open":1474,"high":1523,"low":1097,"close":1175,"Volume":2181012,"Volume MA":1623223.75},{"symbol":"NQ","timeframe":"1M","time":1001887200,"open":1171,"high":1493,"low":1136,"close":1369,"Volume":3964161,"Volume MA":1802118.45},{"symbol":"NQ","timeframe":"1M","time":1004569200,"open":1364.5,"high":1648,"low":1360.5,"close":1598,"Volume":3263778,"Volume MA":1936678.5},{"symbol":"NQ","timeframe":"1M","time":1007334000,"open":1590,"high":1738,"low":1557.5,"close":1583.5,"Volume":2358930,"Volume MA":2024661.55},{"symbol":"NQ","timeframe":"1M","time":1009839600,"open":1577.5,"high":1717,"low":1484,"close":1553.5,"Volume":3719312,"Volume MA":2173391.9},{"symbol":"NQ","timeframe":"1M","time":1012518000,"open":1549.5,"high":1565.5,"low":1330.5,"close":1360.5,"Volume":3843644,"Volume MA":2329068.65},{"symbol":"NQ","timeframe":"1M","time":1014937200,"open":1360,"high":1583,"low":1358,"close":1459.5,"Volume":3412148,"Volume MA":2461881.75},{"symbol":"NQ","timeframe":"1M","time":1017615600,"open":1454,"high":1489.5,"low":1231,"close":1280,"Volume":4227364,"Volume MA":2629094.35},{"symbol":"NQ","timeframe":"1M","time":1020204000,"open":1279.5,"high":1354,"low":1144.5,"close":1209.5,"Volume":4835568,"Volume MA":2812730.7},{"symbol":"NQ","timeframe":"1M","time":1023055200,"open":1209.5,"high":1219.5,"low":974,"close":1054,"Volume":4427024,"Volume MA":2954640.6},{"symbol":"NQ","timeframe":"1M","time":1025474400,"open":1054.5,"high":1073.5,"low":873,"close":961.5,"Volume":6038526,"Volume MA":3180655.55},{"symbol":"NQ","timeframe":"1M","time":1028152800,"open":958.5,"high":1055,"low":857,"close":943.5,"Volume":4305028,"Volume MA":3324045.25},{"symbol":"NQ","timeframe":"1M","time":1030917600,"open":942,"high":980.5,"low":826,"close":837,"Volume":4240411,"Volume MA":3442105.65},{"symbol":"NQ","timeframe":"1M","time":1033423200,"open":835.5,"high":1014.5,"low":797.5,"close":991.5,"Volume":6252221,"Volume MA":3657656.75},{"symbol":"NQ","timeframe":"1M","time":1036105200,"open":991.5,"high":1145,"low":973.5,"close":1117,"Volume":5031103,"Volume MA":3784187.75},{"symbol":"NQ","timeframe":"1M","time":1038783600,"open":1112.5,"high":1157.5,"low":979,"close":987,"Volume":4239842,"Volume MA":3850029.55},{"symbol":"NQ","timeframe":"1M","time":1041375600,"open":992,"high":1108.5,"low":965,"close":984.5,"Volume":5338706,"Volume MA":3977185.45},{"symbol":"NQ","timeframe":"1M","time":1044226800,"open":984,"high":1022,"low":938.5,"close":1010.5,"Volume":4879522,"Volume MA":4080077.7},{"symbol":"NQ","timeframe":"1M","time":1046646000,"open":1014.5,"high":1103.5,"low":945,"close":1021,"Volume":5335553,"Volume MA":4223071.1},{"symbol":"NQ","timeframe":"1M","time":1049151600,"open":1019,"high":1129.5,"low":1015.5,"close":1108,"Volume":5130873,"Volume MA":4351236.3},{"symbol":"NQ","timeframe":"1M","time":1051740000,"open":1107,"high":1202.5,"low":1095,"close":1199,"Volume":5238059,"Volume MA":4504088.65},{"symbol":"NQ","timeframe":"1M","time":1054504800,"open":1198.5,"high":1266.5,"low":1180,"close":1204.5,"Volume":5960921,"Volume MA":4603926.65},{"symbol":"NQ","timeframe":"1M","time":1057010400,"open":1206,"high":1319.5,"low":1179,"close":1279,"Volume":6365998,"Volume MA":4759037.65},{"symbol":"NQ","timeframe":"1M","time":1059688800,"open":1278.5,"high":1346,"low":1204,"close":1342,"Volume":4920697,"Volume MA":4887126},{"symbol":"NQ","timeframe":"1M","time":1062367200,"open":1341,"high":1405,"low":1303,"close":1306,"Volume":6770142,"Volume MA":5039667.5},{"symbol":"NQ","timeframe":"1M","time":1064959200,"open":1305.5,"high":1445,"low":1304.5,"close":1418,"Volume":6598658,"Volume MA":5177418.2},{"symbol":"NQ","timeframe":"1M","time":1067814000,"open":1412.5,"high":1458.5,"low":1356.5,"close":1425,"Volume":5496232,"Volume MA":5281622.4},{"symbol":"NQ","timeframe":"1M","time":1070233200,"open":1424,"high":1479,"low":1372.5,"close":1468,"Volume":5132301,"Volume MA":5326869.25},{"symbol":"NQ","timeframe":"1M","time":1072911600,"open":1473,"high":1563,"low":1460.5,"close":1495,"Volume":6641608,"Volume MA":5417171.25},{"symbol":"NQ","timeframe":"1M","time":1075676400,"open":1494,"high":1525.5,"low":1452,"close":1471.5,"Volume":5858370,"Volume MA":5488738.55},{"symbol":"NQ","timeframe":"1M","time":1078095600,"open":1473,"high":1496,"low":1365.5,"close":1441.5,"Volume":7497726,"Volume MA":5561698.55},{"symbol":"NQ","timeframe":"1M","time":1080774000,"open":1443.5,"high":1511,"low":1399.5,"close":1403,"Volume":6385429,"Volume MA":5665718.6},{"symbol":"NQ","timeframe":"1M","time":1083535200,"open":1399.5,"high":1471.5,"low":1372.5,"close":1468,"Volume":7055801,"Volume MA":5806488.1},{"symbol":"NQ","timeframe":"1M","time":1086040800,"open":1466,"high":1528.5,"low":1441.5,"close":1521,"Volume":5596073,"Volume MA":5773680.7},{"symbol":"NQ","timeframe":"1M","time":1088632800,"open":1521.5,"high":1525.5,"low":1360,"close":1402.5,"Volume":7512819,"Volume MA":5897766.5},{"symbol":"NQ","timeframe":"1M","time":1091397600,"open":1400,"high":1410.5,"low":1302,"close":1370,"Volume":6117029,"Volume MA":5991625.85},{"symbol":"NQ","timeframe":"1M","time":1093989600,"open":1369.5,"high":1446.5,"low":1360,"close":1417.5,"Volume":6122605,"Volume MA":6030820.8},{"symbol":"NQ","timeframe":"1M","time":1096581600,"open":1417,"high":1500.5,"low":1412,"close":1490,"Volume":7318577,"Volume MA":6152773.55},{"symbol":"NQ","timeframe":"1M","time":1099263600,"open":1481,"high":1596.5,"low":1481,"close":1573,"Volume":6108273,"Volume MA":6191409.55},{"symbol":"NQ","timeframe":"1M","time":1101855600,"open":1578.5,"high":1645,"low":1574.5,"close":1628.5,"Volume":4974031,"Volume MA":6183567.45},{"symbol":"NQ","timeframe":"1M","time":1104706800,"open":1628,"high":1644,"low":1484.5,"close":1524,"Volume":7173057,"Volume MA":6280317.35},{"symbol":"NQ","timeframe":"1M","time":1107212400,"open":1522.5,"high":1565,"low":1490.5,"close":1513,"Volume":6146733,"Volume MA":6289607.95},{"symbol":"NQ","timeframe":"1M","time":1109631600,"open":1513.5,"high":1555,"low":1463.5,"close":1491,"Volume":6730294,"Volume MA":6307822.75},{"symbol":"NQ","timeframe":"1M","time":1112310000,"open":1491.5,"high":1511.5,"low":1397.5,"close":1425.5,"Volume":7235602,"Volume MA":6423568},{"symbol":"NQ","timeframe":"1M","time":1114984800,"open":1426,"high":1558.5,"low":1419,"close":1545,"Volume":5732308,"Volume MA":6371676.3},{"symbol":"NQ","timeframe":"1M","time":1117576800,"open":1544,"high":1576.5,"low":1499.5,"close":1503,"Volume":5698610,"Volume MA":6326673.9},{"symbol":"NQ","timeframe":"1M","time":1120168800,"open":1502,"high":1630,"low":1465,"close":1611.5,"Volume":4894941,"Volume MA":6296609.35},{"symbol":"NQ","timeframe":"1M","time":1122847200,"open":1616,"high":1635.5,"low":1544.5,"close":1584,"Volume":5163337,"Volume MA":6298161.15},{"symbol":"NQ","timeframe":"1M","time":1125525600,"open":1585.5,"high":1634.5,"low":1563.5,"close":1614,"Volume":5113458,"Volume MA":6221753.65},{"symbol":"NQ","timeframe":"1M","time":1128290400,"open":1615.5,"high":1629.5,"low":1523,"close":1586.5,"Volume":6581566,"Volume MA":6257913.45},{"symbol":"NQ","timeframe":"1M","time":1130799600,"open":1578,"high":1710,"low":1574,"close":1675,"Volume":5530885,"Volume MA":6159571.4},{"symbol":"NQ","timeframe":"1M","time":1133391600,"open":1678,"high":1731,"low":1654,"close":1659,"Volume":4323267,"Volume MA":6056463.3},{"symbol":"NQ","timeframe":"1M","time":1136156400,"open":1658,"high":1774,"low":1646,"close":1719.5,"Volume":6906639,"Volume MA":6049005.2},{"symbol":"NQ","timeframe":"1M","time":1138748400,"open":1698.5,"high":1725.5,"low":1642.5,"close":1674.5,"Volume":6118416,"Volume MA":6075122.35},{"symbol":"NQ","timeframe":"1M","time":1141167600,"open":1673,"high":1737.5,"low":1642,"close":1720,"Volume":6857832,"Volume MA":6042373},{"symbol":"NQ","timeframe":"1M","time":1144015200,"open":1724.25,"high":1765.75,"low":1696.25,"close":1711,"Volume":5457341,"Volume MA":6009388.6},{"symbol":"NQ","timeframe":"1M","time":1146434400,"open":1714.5,"high":1728,"low":1557.25,"close":1583,"Volume":7832710,"Volume MA":6094893.85},{"symbol":"NQ","timeframe":"1M","time":1149112800,"open":1583,"high":1636.75,"low":1525.75,"close":1591.5,"Volume":7187677,"Volume MA":6088348.85},{"symbol":"NQ","timeframe":"1M","time":1151877600,"open":1593.5,"high":1603.5,"low":1457.75,"close":1518.75,"Volume":6950986,"Volume MA":6130484.5},{"symbol":"NQ","timeframe":"1M","time":1154383200,"open":1516,"high":1591.5,"low":1481.75,"close":1583,"Volume":6309661,"Volume MA":6197266},{"symbol":"NQ","timeframe":"1M","time":1157061600,"open":1584,"high":1683.25,"low":1561.5,"close":1671.25,"Volume":6438764,"Volume MA":6160551.35},{"symbol":"NQ","timeframe":"1M","time":1159740000,"open":1670.5,"high":1757,"low":1638,"close":1742.75,"Volume":6766131,"Volume MA":6191521.25},{"symbol":"NQ","timeframe":"1M","time":1162335600,"open":1743.25,"high":1826,"low":1701.25,"close":1794.75,"Volume":6505172,"Volume MA":6180265.15},{"symbol":"NQ","timeframe":"1M","time":1164927600,"open":1794.25,"high":1848.75,"low":1762.5,"close":1775,"Volume":4776995,"Volume MA":6057334.8},{"symbol":"NQ","timeframe":"1M","time":1167606000,"open":1780.5,"high":1867.75,"low":1747,"close":1802.5,"Volume":7115855,"Volume MA":6126512.15},{"symbol":"NQ","timeframe":"1M","time":1170284400,"open":1804.5,"high":1857.5,"low":1743.25,"close":1765.5,"Volume":6952475,"Volume MA":6189205.4},{"symbol":"NQ","timeframe":"1M","time":1172703600,"open":1764.5,"high":1831,"low":1704.75,"close":1790.75,"Volume":7892520,"Volume MA":6339084.35},{"symbol":"NQ","timeframe":"1M","time":1175464800,"open":1791.75,"high":1909,"low":1778.25,"close":1879.25,"Volume":4974818,"Volume MA":6329658.4},{"symbol":"NQ","timeframe":"1M","time":1177970400,"open":1876.5,"high":1935.75,"low":1868,"close":1932.25,"Volume":7063869,"Volume MA":6427178.95},{"symbol":"NQ","timeframe":"1M","time":1180648800,"open":1933.5,"high":1975,"low":1881.75,"close":1956,"Volume":7387215,"Volume MA":6467461.4},{"symbol":"NQ","timeframe":"1M","time":1183327200,"open":1955,"high":2077.75,"low":1942.25,"close":1945.75,"Volume":8120222,"Volume MA":6596928.25},{"symbol":"NQ","timeframe":"1M","time":1185919200,"open":1951.5,"high":2006.75,"low":1813.75,"close":1994.75,"Volume":10551899,"Volume MA":6908359.85},{"symbol":"NQ","timeframe":"1M","time":1188770400,"open":1994.75,"high":2124,"low":1947,"close":2114,"Volume":6126330,"Volume MA":6869344.4},{"symbol":"NQ","timeframe":"1M","time":1191189600,"open":2116.25,"high":2253,"low":2108.5,"close":2252.5,"Volume":8914908,"Volume MA":7009169},{"symbol":"NQ","timeframe":"1M","time":1193868000,"open":2252.5,"high":2256.25,"low":1982.25,"close":2094.5,"Volume":11136694,"Volume MA":7223112.1},{"symbol":"NQ","timeframe":"1M","time":1196636400,"open":2092.75,"high":2165,"low":2021,"close":2104.75,"Volume":5919256,"Volume MA":7246207.85},{"symbol":"NQ","timeframe":"1M","time":1199142000,"open":2111.25,"high":2117,"low":1698.25,"close":1847.75,"Volume":11596482,"Volume MA":7434396.45},{"symbol":"NQ","timeframe":"1M","time":1201820400,"open":1835.75,"high":1879,"low":1713,"close":1748.25,"Volume":8062613,"Volume MA":7478143.25},{"symbol":"NQ","timeframe":"1M","time":1204498800,"open":1748,"high":1839.5,"low":1668.75,"close":1790.5,"Volume":8798276,"Volume MA":7570507.75},{"symbol":"NQ","timeframe":"1M","time":1207000800,"open":1785.5,"high":1960.5,"low":1777.25,"close":1923.25,"Volume":6879944,"Volume MA":7599021.9},{"symbol":"NQ","timeframe":"1M","time":1209592800,"open":1922.25,"high":2054.25,"low":1921.5,"close":2035.25,"Volume":7407416,"Volume MA":7647454.5},{"symbol":"NQ","timeframe":"1M","time":1212357600,"open":2037,"high":2062.75,"low":1836,"close":1846,"Volume":9031593,"Volume MA":7760727.6},{"symbol":"NQ","timeframe":"1M","time":1214863200,"open":1849.75,"high":1887.25,"low":1765.25,"close":1853.75,"Volume":10469033,"Volume MA":7958920.65},{"symbol":"NQ","timeframe":"1M","time":1217541600,"open":1854.25,"high":1977.25,"low":1801.75,"close":1875,"Volume":7597223,"Volume MA":8099932.05},{"symbol":"NQ","timeframe":"1M","time":1220220000,"open":1875.25,"high":1915.5,"low":1494,"close":1594.25,"Volume":10511151,"Volume MA":8269696.85},{"symbol":"NQ","timeframe":"1M","time":1222812000,"open":1599.75,"high":1600.25,"low":1136.75,"close":1337,"Volume":12282000,"Volume MA":8536173.1},{"symbol":"NQ","timeframe":"1M","time":1225666800,"open":1340,"high":1389,"low":1017.75,"close":1186,"Volume":7296261,"Volume MA":8506360.15},{"symbol":"NQ","timeframe":"1M","time":1228086000,"open":1185.75,"high":1252.5,"low":1089.5,"close":1212.5,"Volume":5870642,"Volume MA":8551151.35},{"symbol":"NQ","timeframe":"1M","time":1230764400,"open":1211,"high":1287,"low":1132,"close":1179.25,"Volume":5702041,"Volume MA":8483059.95},{"symbol":"NQ","timeframe":"1M","time":1233529200,"open":1181,"high":1286,"low":1107.25,"close":1117,"Volume":6783740,"Volume MA":8452886.2},{"symbol":"NQ","timeframe":"1M","time":1235948400,"open":1114.25,"high":1281.75,"low":1040.25,"close":1237.5,"Volume":8046979,"Volume MA":8449224.05},{"symbol":"NQ","timeframe":"1M","time":1238536800,"open":1228,"high":1417.25,"low":1210,"close":1393.5,"Volume":6381613,"Volume MA":8240709.75},{"symbol":"NQ","timeframe":"1M","time":1241128800,"open":1388.75,"high":1442.75,"low":1336.5,"close":1435.5,"Volume":6236963,"Volume MA":8246241.4},{"symbol":"NQ","timeframe":"1M","time":1243807200,"open":1434,"high":1517.75,"low":1412,"close":1476.25,"Volume":6065493,"Volume MA":8103770.65},{"symbol":"NQ","timeframe":"1M","time":1246399200,"open":1476.5,"high":1632,"low":1392.5,"close":1602,"Volume":6238277,"Volume MA":7858849.8},{"symbol":"NQ","timeframe":"1M","time":1249250400,"open":1601.25,"high":1668.5,"low":1561.25,"close":1625,"Volume":5943514,"Volume MA":7860062.7},{"symbol":"NQ","timeframe":"1M","time":1251756000,"open":1625,"high":1753.25,"low":1584.5,"close":1717.5,"Volume":6068923,"Volume MA":7583684.75},{"symbol":"NQ","timeframe":"1M","time":1254348000,"open":1716,"high":1779.25,"low":1649.75,"close":1665.5,"Volume":7043481,"Volume MA":7532728.15},{"symbol":"NQ","timeframe":"1M","time":1257116400,"open":1661,"high":1813.75,"low":1650.25,"close":1767.5,"Volume":5676433,"Volume MA":7376636},{"symbol":"NQ","timeframe":"1M","time":1259622000,"open":1766.5,"high":1882,"low":1758.75,"close":1858.75,"Volume":4985741,"Volume MA":7281925.85},{"symbol":"NQ","timeframe":"1M","time":1262559600,"open":1865.5,"high":1900,"low":1731.75,"close":1739.25,"Volume":6702513,"Volume MA":7246680.7},{"symbol":"NQ","timeframe":"1M","time":1264978800,"open":1740,"high":1833,"low":1710.75,"close":1818.5,"Volume":6170647,"Volume MA":7103633.4},{"symbol":"NQ","timeframe":"1M","time":1267398000,"open":1821.25,"high":1974.25,"low":1821.25,"close":1955.75,"Volume":5845267,"Volume MA":6872445.1},{"symbol":"NQ","timeframe":"1M","time":1270072800,"open":1955.75,"high":2058.75,"low":1940.75,"close":1998.5,"Volume":5934028,"Volume MA":6789285.35},{"symbol":"NQ","timeframe":"1M","time":1272837600,"open":2002.25,"high":2038,"low":1730.25,"close":1852,"Volume":8659018,"Volume MA":6696678.7},{"symbol":"NQ","timeframe":"1M","time":1275256800,"open":1852,"high":1941,"low":1733,"close":1738,"Volume":7388161,"Volume MA":6451986.75},{"symbol":"NQ","timeframe":"1M","time":1277935200,"open":1736.25,"high":1900.75,"low":1698,"close":1862.25,"Volume":6902737,"Volume MA":6432310.55},{"symbol":"NQ","timeframe":"1M","time":1280700000,"open":1868.75,"high":1918,"low":1744,"close":1766.5,"Volume":6607964,"Volume MA":6469176.65},{"symbol":"NQ","timeframe":"1M","time":1283292000,"open":1773.25,"high":2032,"low":1770.5,"close":1995.5,"Volume":6698778,"Volume MA":6519013.5},{"symbol":"NQ","timeframe":"1M","time":1285884000,"open":1995.75,"high":2136.75,"low":1961,"close":2122,"Volume":6244859,"Volume MA":6492069.45},{"symbol":"NQ","timeframe":"1M","time":1288562400,"open":2125,"high":2198,"low":2083.5,"close":2117,"Volume":6054988,"Volume MA":6392469.9},{"symbol":"NQ","timeframe":"1M","time":1291158000,"open":2115,"high":2239,"low":2110.75,"close":2216,"Volume":3861176,"Volume MA":6266448.05},{"symbol":"NQ","timeframe":"1M","time":1294009200,"open":2220,"high":2346.5,"low":2219.25,"close":2280,"Volume":4982701,"Volume MA":6203734.95},{"symbol":"NQ","timeframe":"1M","time":1296514800,"open":2284,"high":2403,"low":2280.25,"close":2350.75,"Volume":4758968,"Volume MA":6138408.7},{"symbol":"NQ","timeframe":"1M","time":1298934000,"open":2351,"high":2378.75,"low":2185.75,"close":2336.25,"Volume":7366267,"Volume MA":6194808.2},{"symbol":"NQ","timeframe":"1M","time":1301608800,"open":2339,"high":2415.75,"low":2250.25,"close":2400.75,"Volume":4908808,"Volume MA":6143072.9},{"symbol":"NQ","timeframe":"1M","time":1304287200,"open":2408,"high":2428,"low":2281,"close":2371.75,"Volume":5938726,"Volume MA":6136563.05},{"symbol":"NQ","timeframe":"1M","time":1306879200,"open":2375.5,"high":2380.75,"low":2174,"close":2321,"Volume":6177226,"Volume MA":6093250.3},{"symbol":"NQ","timeframe":"1M","time":1309471200,"open":2318.75,"high":2435.5,"low":2314.5,"close":2359.25,"Volume":5268787,"Volume MA":6072868},{"symbol":"NQ","timeframe":"1M","time":1312149600,"open":2386,"high":2395,"low":1972.25,"close":2240.75,"Volume":8870184,"Volume MA":6267090.15},{"symbol":"NQ","timeframe":"1M","time":1314828000,"open":2243.5,"high":2332.5,"low":2108.25,"close":2134.5,"Volume":7354909,"Volume MA":6299709.95},{"symbol":"NQ","timeframe":"1M","time":1317592800,"open":2126.5,"high":2408.75,"low":2035.75,"close":2356,"Volume":6812541,"Volume MA":6331804.65},{"symbol":"NQ","timeframe":"1M","time":1320098400,"open":2353.25,"high":2399.5,"low":2135.75,"close":2295,"Volume":5804709,"Volume MA":6329776.75},{"symbol":"NQ","timeframe":"1M","time":1322694000,"open":2293.25,"high":2344.75,"low":2204.25,"close":2274.5,"Volume":4253894,"Volume MA":6245770.05},{"symbol":"NQ","timeframe":"1M","time":1325458800,"open":2312.5,"high":2478.5,"low":2302.5,"close":2464.25,"Volume":3622979,"Volume MA":5993968.1},{"symbol":"NQ","timeframe":"1M","time":1328050800,"open":2455,"high":2645.25,"low":2453.5,"close":2623,"Volume":4272002,"Volume MA":5838160.15},{"symbol":"NQ","timeframe":"1M","time":1330556400,"open":2623.75,"high":2790.25,"low":2575,"close":2750.75,"Volume":5305907,"Volume MA":5758318.65},{"symbol":"NQ","timeframe":"1M","time":1333317600,"open":2758,"high":2791.5,"low":2624.75,"close":2719.25,"Volume":5653930,"Volume MA":5710616.95},{"symbol":"NQ","timeframe":"1M","time":1335823200,"open":2719.5,"high":2753,"low":2465,"close":2524,"Volume":6425137,"Volume MA":5696934.9},{"symbol":"NQ","timeframe":"1M","time":1338501600,"open":2520,"high":2628.25,"low":2433.75,"close":2609.75,"Volume":5478733,"Volume MA":5658628.6},{"symbol":"NQ","timeframe":"1M","time":1341180000,"open":2612,"high":2658,"low":2516.5,"close":2636.5,"Volume":4852082,"Volume MA":5598483.3},{"symbol":"NQ","timeframe":"1M","time":1343772000,"open":2634.75,"high":2802.5,"low":2600,"close":2771,"Volume":4445605,"Volume MA":5627704.75},{"symbol":"NQ","timeframe":"1M","time":1346623200,"open":2773,"high":2871.75,"low":2742.75,"close":2792,"Volume":4453647,"Volume MA":5601252.05},{"symbol":"NQ","timeframe":"1M","time":1349042400,"open":2789,"high":2840.75,"low":2604.5,"close":2640.5,"Volume":5577603,"Volume MA":5642183.8},{"symbol":"NQ","timeframe":"1M","time":1351720800,"open":2634.25,"high":2694,"low":2492,"close":2675.75,"Volume":5842629,"Volume MA":5566001.9},{"symbol":"NQ","timeframe":"1M","time":1354489200,"open":2676,"high":2713.75,"low":2580,"close":2655.25,"Volume":4889828,"Volume MA":5565052.9},{"symbol":"NQ","timeframe":"1M","time":1356994800,"open":2686.25,"high":2768.75,"low":2686.25,"close":2725,"Volume":4419673,"Volume MA":5489100.25},{"symbol":"NQ","timeframe":"1M","time":1359673200,"open":2733,"high":2786.5,"low":2689,"close":2738,"Volume":4350567,"Volume MA":5397767.3},{"symbol":"NQ","timeframe":"1M","time":1362092400,"open":2738,"high":2817,"low":2711.75,"close":2811,"Volume":4315466,"Volume MA":5350101.25},{"symbol":"NQ","timeframe":"1M","time":1364767200,"open":2811,"high":2884.25,"low":2724,"close":2880,"Volume":5224810,"Volume MA":5167832.55},{"symbol":"NQ","timeframe":"1M","time":1367359200,"open":2884,"high":3053.5,"low":2862.25,"close":2980.25,"Volume":4539251,"Volume MA":5027049.65},{"symbol":"NQ","timeframe":"1M","time":1370210400,"open":2981,"high":3007,"low":2817.75,"close":2901.25,"Volume":5787862,"Volume MA":4975815.7},{"symbol":"NQ","timeframe":"1M","time":1372629600,"open":2902.75,"high":3105,"low":2894.25,"close":3083,"Volume":4221402,"Volume MA":4896650.35},{"symbol":"NQ","timeframe":"1M","time":1375308000,"open":3088.75,"high":3148,"low":3052.5,"close":3073.5,"Volume":4679452,"Volume MA":4917928.25},{"symbol":"NQ","timeframe":"1M","time":1378072800,"open":3088.75,"high":3241.5,"low":3076,"close":3209,"Volume":4596986,"Volume MA":4966628.6},{"symbol":"NQ","timeframe":"1M","time":1380578400,"open":3221.25,"high":3401.75,"low":3110.75,"close":3369,"Volume":6073438,"Volume MA":5056700.4},{"symbol":"NQ","timeframe":"1M","time":1383256800,"open":3377.25,"high":3496.5,"low":3310,"close":3487.5,"Volume":4273900,"Volume MA":5005100.05},{"symbol":"NQ","timeframe":"1M","time":1385938800,"open":3493,"high":3594.75,"low":3415.25,"close":3583.75,"Volume":4339146,"Volume MA":4939360.85},{"symbol":"NQ","timeframe":"1M","time":1388530800,"open":3575.75,"high":3635.25,"low":3454.25,"close":3514,"Volume":5637514,"Volume MA":4899979.7},{"symbol":"NQ","timeframe":"1M","time":1391382000,"open":3514,"high":3722.5,"low":3412,"close":3695.25,"Volume":5220912,"Volume MA":4887088.65},{"symbol":"NQ","timeframe":"1M","time":1393801200,"open":3678,"high":3740.5,"low":3535.25,"close":3586.25,"Volume":6796203,"Volume MA":4984294.7},{"symbol":"NQ","timeframe":"1M","time":1396303200,"open":3583.25,"high":3669,"low":3404.75,"close":3573.25,"Volume":7764368,"Volume MA":5150232.85},{"symbol":"NQ","timeframe":"1M","time":1398895200,"open":3577,"high":3740.5,"low":3497.5,"close":3735.5,"Volume":5523271,"Volume MA":5203714.05},{"symbol":"NQ","timeframe":"1M","time":1401660000,"open":3735,"high":3851.25,"low":3707.25,"close":3840.5,"Volume":4578621,"Volume MA":5153764.95},{"symbol":"NQ","timeframe":"1M","time":1404165600,"open":3847,"high":3991.25,"low":3831.5,"close":3884.75,"Volume":5297117,"Volume MA":5126489.35},{"symbol":"NQ","timeframe":"1M","time":1406844000,"open":3890.5,"high":4086,"low":3826.5,"close":4082,"Volume":4756416,"Volume MA":5119818.75},{"symbol":"NQ","timeframe":"1M","time":1409522400,"open":4078.75,"high":4118.75,"low":3998,"close":4044.75,"Volume":6355869,"Volume MA":5216628.55},{"symbol":"NQ","timeframe":"1M","time":1412114400,"open":4036.25,"high":4163.5,"low":3684,"close":4150.5,"Volume":10098897,"Volume MA":5504045.05},{"symbol":"NQ","timeframe":"1M","time":1414969200,"open":4150.25,"high":4348,"low":4119.75,"close":4338.25,"Volume":4001590,"Volume MA":5488351.25},{"symbol":"NQ","timeframe":"1M","time":1417388400,"open":4330.75,"high":4335.5,"low":4080.75,"close":4232.75,"Volume":6212331,"Volume MA":5537727.3},{"symbol":"NQ","timeframe":"1M","time":1420066800,"open":4240.25,"high":4286.25,"low":4041.5,"close":4141.25,"Volume":6832557,"Volume MA":5652392.6},{"symbol":"NQ","timeframe":"1M","time":1422831600,"open":4143.5,"high":4464.75,"low":4085.5,"close":4442.5,"Volume":3982918,"Volume MA":5562145.4},{"symbol":"NQ","timeframe":"1M","time":1425250800,"open":4447,"high":4483.25,"low":4270,"close":4329.5,"Volume":5360371,"Volume MA":5619093.85},{"symbol":"NQ","timeframe":"1M","time":1427839200,"open":4321.75,"high":4555.5,"low":4259,"close":4408.25,"Volume":4615552,"Volume MA":5615898.85},{"symbol":"NQ","timeframe":"1M","time":1430431200,"open":4414,"high":4551,"low":4332.5,"close":4511,"Volume":3878048,"Volume MA":5579951.95},{"symbol":"NQ","timeframe":"1M","time":1433109600,"open":4514,"high":4555.25,"low":4368.25,"close":4390.25,"Volume":4856236,"Volume MA":5519091.85},{"symbol":"NQ","timeframe":"1M","time":1435701600,"open":4392.75,"high":4686,"low":4331.75,"close":4585,"Volume":5098591,"Volume MA":5560326.4},{"symbol":"NQ","timeframe":"1M","time":1438552800,"open":4583.25,"high":4629,"low":3908.25,"close":4271.75,"Volume":7403507,"Volume MA":5713544.45},{"symbol":"NQ","timeframe":"1M","time":1441058400,"open":4266,"high":4441.75,"low":4040.75,"close":4163,"Volume":5947018,"Volume MA":5729019.65},{"symbol":"NQ","timeframe":"1M","time":1443650400,"open":4154,"high":4690.25,"low":4111.5,"close":4643.25,"Volume":5775819,"Volume MA":5756765},{"symbol":"NQ","timeframe":"1M","time":1446418800,"open":4644.5,"high":4729.75,"low":4455,"close":4668.75,"Volume":4423547,"Volume MA":5638132.2},{"symbol":"NQ","timeframe":"1M","time":1448924400,"open":4678.75,"high":4739.5,"low":4471.25,"close":4587.75,"Volume":5485303,"Volume MA":5524178.95},{"symbol":"NQ","timeframe":"1M","time":1451602800,"open":4592.5,"high":4606.75,"low":3983.5,"close":4263,"Volume":8219688,"Volume MA":5658999.8},{"symbol":"NQ","timeframe":"1M","time":1454281200,"open":4263.25,"high":4309.25,"low":3862.5,"close":4201.25,"Volume":6808865,"Volume MA":5770512},{"symbol":"NQ","timeframe":"1M","time":1456786800,"open":4199.25,"high":4510.25,"low":4180.25,"close":4476.25,"Volume":5205469,"Volume MA":5765929.6},{"symbol":"NQ","timeframe":"1M","time":1459461600,"open":4477.75,"high":4584.5,"low":4296.75,"close":4331.5,"Volume":5005508,"Volume MA":5778384.2},{"symbol":"NQ","timeframe":"1M","time":1462140000,"open":4337,"high":4528.25,"low":4271,"close":4524.25,"Volume":4807424,"Volume MA":5700961.95},{"symbol":"NQ","timeframe":"1M","time":1464732000,"open":4522,"high":4545.5,"low":4167.75,"close":4407,"Volume":5478999,"Volume MA":5469967.05},{"symbol":"NQ","timeframe":"1M","time":1467324000,"open":4397,"high":4736.5,"low":4365.75,"close":4726.75,"Volume":3856103,"Volume MA":5462692.7},{"symbol":"NQ","timeframe":"1M","time":1470002400,"open":4737.5,"high":4836.75,"low":4681.75,"close":4773.75,"Volume":4050048,"Volume MA":5354578.55},{"symbol":"NQ","timeframe":"1M","time":1472680800,"open":4774,"high":4892.25,"low":4625.25,"close":4870.25,"Volume":5730054,"Volume MA":5299453.4},{"symbol":"NQ","timeframe":"1M","time":1475445600,"open":4867.25,"high":4919.5,"low":4754.5,"close":4796.75,"Volume":4708695,"Volume MA":5335742.25},{"symbol":"NQ","timeframe":"1M","time":1477951200,"open":4802.75,"high":4897.75,"low":4558.5,"close":4816,"Volume":5385003,"Volume MA":5336973.85},{"symbol":"NQ","timeframe":"1M","time":1480546800,"open":4819,"high":4994.5,"low":4701.5,"close":4864,"Volume":3884220,"Volume MA":5300407.25},{"symbol":"NQ","timeframe":"1M","time":1483311600,"open":4876.75,"high":5168.5,"low":4876.75,"close":5112.75,"Volume":3621653,"Volume MA":5287587.5},{"symbol":"NQ","timeframe":"1M","time":1485903600,"open":5132,"high":5361.25,"low":5119.5,"close":5332.25,"Volume":3393613,"Volume MA":5214456.35},{"symbol":"NQ","timeframe":"1M","time":1488322800,"open":5334.5,"high":5452.75,"low":5315,"close":5438.5,"Volume":5179285,"Volume MA":5218491.05},{"symbol":"NQ","timeframe":"1M","time":1491170400,"open":5436.75,"high":5599,"low":5347.5,"close":5580.5,"Volume":4373600,"Volume MA":5066995.7},{"symbol":"NQ","timeframe":"1M","time":1493589600,"open":5581,"high":5819.25,"low":5550.5,"close":5793.25,"Volume":5117422,"Volume MA":5025515.9},{"symbol":"NQ","timeframe":"1M","time":1496268000,"open":5804.75,"high":5907.5,"low":5601,"close":5652.75,"Volume":7846149,"Volume MA":5129032.4},{"symbol":"NQ","timeframe":"1M","time":1499032800,"open":5658,"high":5995.75,"low":5560.25,"close":5882.5,"Volume":5519190,"Volume MA":5183814.55},{"symbol":"NQ","timeframe":"1M","time":1501538400,"open":5884.5,"high":5998,"low":5752.25,"close":5990.75,"Volume":7457583,"Volume MA":5282428.55},{"symbol":"NQ","timeframe":"1M","time":1504216800,"open":5994,"high":6019.75,"low":5842,"close":5982.5,"Volume":6031251,"Volume MA":5173006.7},{"symbol":"NQ","timeframe":"1M","time":1506895200,"open":5984,"high":6258.75,"low":5958.5,"close":6249.75,"Volume":5488235,"Volume MA":5106975.2},{"symbol":"NQ","timeframe":"1M","time":1509487200,"open":6249.75,"high":6429.5,"low":6192.5,"close":6369,"Volume":6378892,"Volume MA":5165646.35},{"symbol":"NQ","timeframe":"1M","time":1512082800,"open":6353.75,"high":6545.75,"low":6231.75,"close":6408.75,"Volume":5715863,"Volume MA":5201164.1},{"symbol":"NQ","timeframe":"1M","time":1514761200,"open":6405,"high":7047.25,"low":6397.75,"close":6962.5,"Volume":6986062,"Volume MA":5310096},{"symbol":"NQ","timeframe":"1M","time":1517439600,"open":6973,"high":7009,"low":6164,"close":6865,"Volume":9676883,"Volume MA":5519990.2},{"symbol":"NQ","timeframe":"1M","time":1519858800,"open":6879.5,"high":7214.5,"low":6421,"close":6594,"Volume":11315921,"Volume MA":5892981.1},{"symbol":"NQ","timeframe":"1M","time":1522620000,"open":6557,"high":6867,"low":6306.75,"close":6613,"Volume":10004148,"Volume MA":6190686.1},{"symbol":"NQ","timeframe":"1M","time":1525125600,"open":6606,"high":7023.5,"low":6538,"close":6977,"Volume":7672062,"Volume MA":6287786.5},{"symbol":"NQ","timeframe":"1M","time":1527804000,"open":6982.5,"high":7358.5,"low":6956,"close":7066.75,"Volume":7630005,"Volume MA":6433852},{"symbol":"NQ","timeframe":"1M","time":1530482400,"open":7068.25,"high":7530,"low":6987.5,"close":7244.75,"Volume":7274283,"Volume MA":6528316},{"symbol":"NQ","timeframe":"1M","time":1533074400,"open":7293,"high":7697,"low":7214.25,"close":7661.25,"Volume":7572257,"Volume MA":6712717.85},{"symbol":"NQ","timeframe":"1M","time":1535925600,"open":7670,"high":7693.75,"low":7393,"close":7655.25,"Volume":8499028,"Volume MA":6956586.6},{"symbol":"NQ","timeframe":"1M","time":1538344800,"open":7672,"high":7728.75,"low":6580.5,"close":6975.5,"Volume":16641451,"Volume MA":7618978.5},{"symbol":"NQ","timeframe":"1M","time":1541023200,"open":6960,"high":7231,"low":6449.5,"close":6949.5,"Volume":13051988,"Volume MA":8012613.65},{"symbol":"NQ","timeframe":"1M","time":1543791600,"open":7041,"high":7139,"low":5820.5,"close":6333.25,"Volume":13318357,"Volume MA":8459851.5},{"symbol":"NQ","timeframe":"1M","time":1546383600,"open":6349.5,"high":6943,"low":6136.5,"close":6914.75,"Volume":10834639,"Volume MA":8745712.35},{"symbol":"NQ","timeframe":"1M","time":1548975600,"open":6911,"high":7168.5,"low":6841,"close":7102.5,"Volume":7694175,"Volume MA":8738113.65},{"symbol":"NQ","timeframe":"1M","time":1551394800,"open":7106.5,"high":7544.75,"low":6965.75,"close":7400.5,"Volume":9821699,"Volume MA":8953239.1},{"symbol":"NQ","timeframe":"1M","time":1554069600,"open":7430,"high":7879.5,"low":7428.5,"close":7800,"Volume":8150702,"Volume MA":8987895.05},{"symbol":"NQ","timeframe":"1M","time":1556661600,"open":7848.75,"high":7872.5,"low":7129.25,"close":7133.5,"Volume":12790997,"Volume MA":9325882.35},{"symbol":"NQ","timeframe":"1M","time":1559512800,"open":7110,"high":7821,"low":6941.25,"close":7693.75,"Volume":8498928,"Volume MA":9476417},{"symbol":"NQ","timeframe":"1M","time":1561932000,"open":7781.5,"high":8051.75,"low":7743,"close":7866.75,"Volume":7912845,"Volume MA":9553114.65},{"symbol":"NQ","timeframe":"1M","time":1564610400,"open":7834,"high":8014.5,"low":7224.5,"close":7690.75,"Volume":13364228,"Volume MA":9935532.9},{"symbol":"NQ","timeframe":"1M","time":1567375200,"open":7628.25,"high":7982.75,"low":7580.75,"close":7770.5,"Volume":8665667,"Volume MA":10019513.15},{"symbol":"NQ","timeframe":"1M","time":1569880800,"open":7784,"high":8141,"low":7474.25,"close":8090.25,"Volume":9465167,"Volume MA":10008927.35},{"symbol":"NQ","timeframe":"1M","time":1572559200,"open":8094.25,"high":8458.75,"low":8084.5,"close":8417.5,"Volume":6721180,"Volume MA":9779190.3},{"symbol":"NQ","timeframe":"1M","time":1575241200,"open":8424.5,"high":8843.5,"low":8168.25,"close":8752.25,"Volume":7246931,"Volume MA":9641329.45},{"symbol":"NQ","timeframe":"1M","time":1577833200,"open":8776.75,"high":9287.25,"low":8678,"close":8997.75,"Volume":12091541,"Volume MA":9862303.4},{"symbol":"NQ","timeframe":"1M","time":1580684400,"open":8982.75,"high":9763,"low":8126.25,"close":8454,"Volume":15436423,"Volume MA":10252624.3},{"symbol":"NQ","timeframe":"1M","time":1583103600,"open":8349.25,"high":9002.5,"low":6628.75,"close":7786.25,"Volume":15789485,"Volume MA":10678384.4},{"symbol":"NQ","timeframe":"1M","time":1585692000,"open":7772.5,"high":9144.75,"low":7376,"close":8988.5,"Volume":9239169,"Volume MA":10761730},{"symbol":"NQ","timeframe":"1M","time":1588284000,"open":8847,"high":9604,"low":8556.25,"close":9560.25,"Volume":9145210,"Volume MA":10794039.1},{"symbol":"NQ","timeframe":"1M","time":1590962400,"open":9513,"high":10296.25,"low":9368.25,"close":10147.25,"Volume":10506180,"Volume MA":10487275.55},{"symbol":"NQ","timeframe":"1M","time":1593554400,"open":10141,"high":11058.5,"low":10076,"close":10890.5,"Volume":12093981,"Volume MA":10439375.2},{"symbol":"NQ","timeframe":"1M","time":1596405600,"open":10933.25,"high":12165,"low":10845.5,"close":12114,"Volume":9551690,"Volume MA":10251041.85},{"symbol":"NQ","timeframe":"1M","time":1598911200,"open":12109.75,"high":12465.25,"low":10656.5,"close":11407.25,"Volume":14684108,"Volume MA":10443515.3},{"symbol":"NQ","timeframe":"1M","time":1601503200,"open":11375,"high":12249,"low":10944.5,"close":11046.25,"Volume":13198308,"Volume MA":10718721.95},{"symbol":"NQ","timeframe":"1M","time":1604271600,"open":11034.5,"high":12408.75,"low":10942.25,"close":12277,"Volume":10330603,"Volume MA":10744167.15},{"symbol":"NQ","timeframe":"1M","time":1606777200,"open":12336,"high":12918.25,"low":12218.25,"close":12885.5,"Volume":8762846,"Volume MA":10774774.35},{"symbol":"NQ","timeframe":"1M","time":1609714800,"open":12889,"high":13599.75,"low":12491.25,"close":12911.25,"Volume":10188559,"Volume MA":10644652.45},{"symbol":"NQ","timeframe":"1M","time":1612134000,"open":12849,"high":13900.5,"low":12662.25,"close":12911,"Volume":10811597,"Volume MA":10760285.9},{"symbol":"NQ","timeframe":"1M","time":1614553200,"open":12957.5,"high":13328.25,"low":12207.25,"close":13089.75,"Volume":14429030,"Volume MA":11086095.15},{"symbol":"NQ","timeframe":"1M","time":1617228000,"open":13094.5,"high":14064,"low":13090.25,"close":13850,"Volume":10121264,"Volume MA":10923946.95},{"symbol":"NQ","timeframe":"1M","time":1619992800,"open":13880.25,"high":13947.5,"low":12915,"close":13686.5,"Volume":10554306,"Volume MA":11018378.9},{"symbol":"NQ","timeframe":"1M","time":1622412000,"open":13699,"high":14598.5,"low":13462.25,"close":14549,"Volume":9625124,"Volume MA":11026376.75},{"symbol":"NQ","timeframe":"1M","time":1625090400,"open":14558.5,"high":15134,"low":14445,"close":14955.75,"Volume":10543085,"Volume MA":11217472},{"symbol":"NQ","timeframe":"1M","time":1627855200,"open":14972.75,"high":15677.25,"low":14710.5,"close":15582.5,"Volume":10457685,"Volume MA":11378009.7},{"symbol":"NQ","timeframe":"1M","time":1630447200,"open":15599.5,"high":15708.75,"low":14670.25,"close":14682.5,"Volume":11965525,"Volume MA":11371708.9},{"symbol":"NQ","timeframe":"1M","time":1633039200,"open":14702.25,"high":15864.75,"low":14367.75,"close":15838.5,"Volume":11176482,"Volume MA":11158711.85},{"symbol":"NQ","timeframe":"1M","time":1635717600,"open":15885.25,"high":16767.5,"low":15768.5,"close":16150.5,"Volume":11796230,"Volume MA":10959049.1},{"symbol":"NQ","timeframe":"1M","time":1638313200,"open":16238.75,"high":16659.5,"low":15492,"close":16320.75,"Volume":12853876,"Volume MA":11139784.45},{"symbol":"NQ","timeframe":"1M","time":1641164400,"open":16356,"high":16564,"low":13706,"close":14905,"Volume":16334953,"Volume MA":11499271.6},{"symbol":"NQ","timeframe":"1M","time":1643670000,"open":14868.75,"high":15260,"low":13025.75,"close":14228,"Volume":13880877,"Volume MA":11668006.45},{"symbol":"NQ","timeframe":"1M","time":1646089200,"open":14219.25,"high":15268.75,"low":12942.5,"close":14868.75,"Volume":13524320,"Volume MA":11739523.4},{"symbol":"NQ","timeframe":"1M","time":1648764000,"open":14918.75,"high":15198,"low":12801.5,"close":12852,"Volume":12864664,"Volume MA":11905172.1},{"symbol":"NQ","timeframe":"1M","time":1651442400,"open":12892.25,"high":13555.25,"low":11491.25,"close":12646.5,"Volume":15692638,"Volume MA":11955598.6},{"symbol":"NQ","timeframe":"1M","time":1654034400,"open":12662.5,"high":12945.25,"low":11068.5,"close":11529.5,"Volume":13480493,"Volume MA":11969707.85},{"symbol":"NQ","timeframe":"1M","time":1656626400,"open":11507.5,"high":13012,"low":11381.75,"close":12971.5,"Volume":12294206,"Volume MA":12067888},{"symbol":"NQ","timeframe":"1M","time":1659304800,"open":12981,"high":13740.75,"low":12247.5,"close":12285.25,"Volume":13999308,"Volume MA":12329711.1},{"symbol":"NQ","timeframe":"1M","time":1661983200,"open":12284.75,"high":12987,"low":11024.25,"close":11035.5,"Volume":15709884,"Volume MA":12605777.35},{"symbol":"NQ","timeframe":"1M","time":1664748000,"open":11030,"high":11734,"low":10484.75,"close":11447.25,"Volume":16031242,"Volume MA":12866759.6},{"symbol":"NQ","timeframe":"1M","time":1667253600,"open":11455,"high":12118.75,"low":10636,"close":12042.25,"Volume":13197524,"Volume MA":12805184.3},{"symbol":"NQ","timeframe":"1M","time":1669849200,"open":12079.25,"high":12339,"low":10758.75,"close":11022.25,"Volume":12126731,"Volume MA":12905457.65},{"symbol":"NQ","timeframe":"1M","time":1672700400,"open":11122.5,"high":12308.5,"low":10751,"close":12152,"Volume":12325282,"Volume MA":12994006.45},{"symbol":"NQ","timeframe":"1M","time":1675206000,"open":12116,"high":12949.75,"low":11923,"close":12072.25,"Volume":12220758,"Volume MA":13123788.15},{"symbol":"NQ","timeframe":"1M","time":1677625200,"open":12041.25,"high":13311.5,"low":11806.25,"close":13301.75,"Volume":15461376,"Volume MA":13369702.7},{"symbol":"NQ","timeframe":"1M","time":1680472800,"open":13262,"high":13348.75,"low":12800,"close":13320.25,"Volume":11679040,"Volume MA":13430770.45},{"symbol":"NQ","timeframe":"1M","time":1682892000,"open":13317,"high":13554.5,"low":13001.75,"close":13534.5,"Volume":7067162,"Volume MA":13185852.3}]